.gitignore
CHANGELOG.md
LICENSE
MANIFEST.in
Makefile
README.md
mkdocs.yml
requirements-dev.txt
requirements.txt
setup.cfg
setup.py
.github/pull_request_template.md
.github/workflows/python_unittest.yaml
docs/CNAME
docs/changelog.md
docs/getting_start.md
docs/index.md
docs/api/decomposition.md
docs/api/discriminant_analysis.md
docs/api/index.md
docs/api/kernel_approximations.md
docs/api/linear_model.md
docs/api/naive_bayes.md
docs/api/neighbors.md
docs/assets/css/custom.css
docs/assets/images/android-chrome-192x192.png
docs/assets/images/android-chrome-512x512.png
docs/assets/images/apple-touch-icon.png
docs/assets/images/favicon-16x16.png
docs/assets/images/favicon-32x32.png
docs/assets/images/favicon.ico
docs/assets/images/torchml-icon.png
docs/assets/images/torchml-logo.png
docs/tutorials/gaussian_nb.md
docs/tutorials/linear_model.md
docs/tutorials/nearest_centroid.md
docs/tutorials/neighbors.md
examples/README.md
tests/__init__.py
tests/unit/__init__.py
tests/unit/discriminant_analysis/__init__.py
tests/unit/discriminant_analysis/linear_discriminant_analysis_test.py
tests/unit/gaussian_naive_bayes/__init__.py
tests/unit/gaussian_naive_bayes/gaussian_nb_test.py
tests/unit/kernel_approximations/__init__.py
tests/unit/kernel_approximations/rbfsampler_test.py
tests/unit/linear_model/__init__.py
tests/unit/linear_model/lasso_test.py
tests/unit/linear_model/linear_regression_test.py
tests/unit/linear_model/ridge_test.py
tests/unit/neighbors/__init__.py
tests/unit/neighbors/k_neighbors_classifier_test.py
tests/unit/neighbors/nearest_centroids_test.py
tests/unit/neighbors/nearest_neighbors_test.py
tests/unit/pca/__init__.py
tests/unit/pca/pca_test.py
tests/unit/quadratic_discriminant_analysis/__init__.py
tests/unit/quadratic_discriminant_analysis/quadratic_discriminant_analysis_test.py
torchml/__init__.py
torchml/_version.py
torchml/base.py
torchml.egg-info/PKG-INFO
torchml.egg-info/SOURCES.txt
torchml.egg-info/dependency_links.txt
torchml.egg-info/requires.txt
torchml.egg-info/top_level.txt
torchml/decomposition/__init__.py
torchml/decomposition/pca.py
torchml/discriminant_analysis/__init__.py
