Metadata-Version: 2.1
Name: torchml
Version: 0.1.0
Summary: Classical ML on top of PyTorch
Home-page: https://learnables.github.com/torchml
Author: Seb Arnold
Author-email: smr.arnold@gmail.com
License: License :: OSI Approved :: Apache Software License
Download-URL: https://github.com/learnables/torchml/archive/0.1.0.zip
Platform: UNKNOWN
License-File: LICENSE
